combos_stat/__init__.py
combos_stat/banner.txt
combos_stat/version.json
combos_stat/bin/__init__.py
combos_stat/bin/_batch.py
combos_stat/bin/_job.py
combos_stat/bin/_merge.py
combos_stat/bin/_parallel.py
combos_stat/bin/_plot.py
combos_stat/bin/_stat.py
combos_stat/bin/main.py
combos_stat/plot/__init__.py
combos_stat/plot/boxplot_tpl.py
combos_stat/plot/pointplot_tpl.py
combos_stat/plot/process_data.py
combos_stat/stat/__init__.py
combos_stat/util/__init__.py
combos_stat-1.0.3.dist-info/METADATA
combos_stat-1.0.3.dist-info/WHEEL
combos_stat-1.0.3.dist-info/entry_points.txt
combos_stat-1.0.3.dist-info/top_level.txt
combos_stat-1.0.3.dist-info/RECORD
